{"meta":{"format":"JSON","version":"1.1.0","projectId":"go-potty-portal","resourcePath":["locations"],"recursive":false,"creationTime":1743778143,"app":"firefoo"},"data":{"1mJ5PEtu3e0Z7YPBXBOF":{"address_city":null,"address_country":null,"address_line1":null,"address_line2":null,"address_postal_code":null,"address_region":null,"created_at":{"__time__":"2025-02-19T16:17:08.278Z"},"created_by":"6kOB3lYQlqeD8WHlANXcUVc2Z7v1","location_type":"location","name":"Laan van NOI","organisation_id":"G7BkXTuV6xKtvFdmTFsz","updated_at":{"__time__":"2025-02-19T16:17:08.278Z"},"updated_by":"6kOB3lYQlqeD8WHlANXcUVc2Z7v1","__collections__":{}},"1s8qWAms7ynouWaoJFLB":{"address_city":null,"address_country":null,"address_line1":null,"address_line2":null,"address_postal_code":null,"address_region":null,"created_at":{"__time__":"2025-03-03T17:16:40.147Z"},"created_by":"6kOB3lYQlqeD8WHlANXcUVc2Z7v1","location_type":"location","name":"POA Rollebol","organisation_id":"TEINbvmlbCMJvXCrYPcn","updated_at":{"__time__":"2025-03-03T17:16:40.147Z"},"updated_by":"6kOB3lYQlqeD8WHlANXcUVc2Z7v1","__collections__":{}},"2pr4K8mNqLvWxYhS9tB3":{"address_city":"Den Haag","address_country":"Netherlands","address_line1":"Prinsegracht 186","address_line2":"","address_postal_code":"2512 GG","address_region":"Zuid-Holland","created_at":{"__time__":"2024-01-15T12:00:00.000Z"},"created_by":"QkfQFGJNQTZIcN3irS9JXfYWeAM2","location_type":"childcare","name":"2Prinsjes","organisation_id":"xK2P9mNqRtYvWzL4HjB8","updated_at":{"__time__":"2024-01-15T12:00:00.000Z"},"updated_by":"QkfQFGJNQTZIcN3irS9JXfYWeAM2","__collections__":{}},"330M93k1oCr0gjWySf0B":{"address_city":null,"address_country":null,"address_line1":null,"address_line2":null,"address_postal_code":null,"address_region":null,"created_at":{"__time__":"2025-01-23T20:43:28.368Z"},"created_by":"wTU25DhANfjrJuUVsfFcFrxcv6xF","location_type":"childcare","name":"Warmoesland","organisation_id":"aCLqsMmDTDnaObYWmrs3","updated_at":{"__time__":"2025-02-17T16:00:00.000Z"},"updated_by":"6kOB3lYQlqeD8WHlANXcUVc2Z7v1","__collections__":{}},"3E1SksIIj96xeIu5zkR7":{"address_city":null,"address_country":null,"address_line1":null,"address_line2":null,"address_postal_code":null,"address_region":null,"created_at":{"__time__":"2025-01-23T20:43:20.306Z"},"created_by":"wTU25DhANfjrJuUVsfFcFrxcv6xF","location_type":"childcare","name":"Achterdijkshoorn","organisation_id":"aCLqsMmDTDnaObYWmrs3","updated_at":{"__time__":"2025-02-17T16:00:00.000Z"},"updated_by":"6kOB3lYQlqeD8WHlANXcUVc2Z7v1","__collections__":{}},"3pn5L9mRqMwXzJhT0uC4":{"address_city":"Den Haag","address_country":"Netherlands","address_line1":"Doedijnsstraat 8","address_line2":"","address_postal_code":"2526 ED","address_region":"Zuid-Holland","created_at":{"__time__":"2024-01-15T12:00:00.000Z"},"created_by":"QkfQFGJNQTZIcN3irS9JXfYWeAM2","location_type":"childcare","name":"2Penselen","organisation_id":"xK2P9mNqRtYvWzL4HjB8","updated_at":{"__time__":"2024-01-15T12:00:00.000Z"},"updated_by":"QkfQFGJNQTZIcN3irS9JXfYWeAM2","__collections__":{}},"4qs6M0nSrNxAkKhU1vD5":{"address_city":"Den Haag","address_country":"Netherlands","address_line1":"Duinkerksestraat 7","address_line2":"","address_postal_code":"2587 VS","address_region":"Zuid-Holland","created_at":{"__time__":"2024-01-15T12:00:00.000Z"},"created_by":"QkfQFGJNQTZIcN3irS9JXfYWeAM2","location_type":"childcare","name":"2Karpers","organisation_id":"xK2P9mNqRtYvWzL4HjB8","updated_at":{"__time__":"2024-01-15T12:00:00.000Z"},"updated_by":"QkfQFGJNQTZIcN3irS9JXfYWeAM2","__collections__":{}},"4qu5K406ZWQYlCTYLZqK":{"address_city":null,"address_country":null,"address_line1":null,"address_line2":null,"address_postal_code":null,"address_region":null,"created_at":{"__time__":"2025-03-03T17:31:53.137Z"},"created_by":"6kOB3lYQlqeD8WHlANXcUVc2Z7v1","location_type":"location","name":"'t Schaepje","organisation_id":"NoDNUx5HLi0gvbkxAJdT","updated_at":{"__time__":"2025-03-03T17:31:53.137Z"},"updated_by":"6kOB3lYQlqeD8WHlANXcUVc2Z7v1","__collections__":{}},"5rt7N1oTsPyBlLhV2wE6":{"address_city":"Den Haag","address_country":"Netherlands","address_line1":"Duinkerksestraat 1","address_line2":"","address_postal_code":"2587 VS","address_region":"Zuid-Holland","created_at":{"__time__":"2024-01-15T12:00:00.000Z"},"created_by":"QkfQFGJNQTZIcN3irS9JXfYWeAM2","location_type":"childcare","name":"2Hindes","organisation_id":"xK2P9mNqRtYvWzL4HjB8","updated_at":{"__time__":"2024-01-15T12:00:00.000Z"},"updated_by":"QkfQFGJNQTZIcN3irS9JXfYWeAM2","__collections__":{}},"6YmTpKqNxZniXtqeVZUl":{"address_city":null,"address_country":null,"address_line1":null,"address_line2":null,"address_postal_code":null,"address_region":null,"created_at":{"__time__":"2024-07-03T15:56:38.821Z"},"created_by":"","location_type":"location","name":"De Stadstuin","organisation_id":"QaGXPwQLLLdQp3L1FGAL","updated_at":{"__time__":"2024-07-03T15:56:38.821Z"},"updated_by":"","__collections__":{}},"9COegJ0tQsXBhRqhpzrK":{"address_city":null,"address_country":null,"address_line1":null,"address_line2":null,"address_postal_code":null,"address_region":null,"created_at":{"__time__":"2024-07-03T15:57:09.820Z"},"created_by":"","location_type":"location","name":"De Achtsprong","organisation_id":"QaGXPwQLLLdQp3L1FGAL","updated_at":{"__time__":"2024-07-03T15:57:09.820Z"},"updated_by":"","__collections__":{}},"9K3IS3dK2uoDDlAvI5JW":{"address_city":null,"address_country":null,"address_line1":null,"address_line2":null,"address_postal_code":null,"address_region":null,"created_at":{"__time__":"2025-03-03T17:16:40.147Z"},"created_by":"6kOB3lYQlqeD8WHlANXcUVc2Z7v1","location_type":"location","name":"KDV Holderdebolder","organisation_id":"TEINbvmlbCMJvXCrYPcn","updated_at":{"__time__":"2025-03-03T17:16:40.147Z"},"updated_by":"6kOB3lYQlqeD8WHlANXcUVc2Z7v1","__collections__":{}},"CVqNY66FNqB7YkKMeS8r":{"address_city":"Achtmaal","address_country":"Netherlands","address_line1":"Van den Berghstraat 2","address_line2":"","address_postal_code":"4885 AH","address_region":"Noord-Brabant","created_at":{"__time__":"2024-12-02T22:00:00.000Z"},"created_by":"QkfQFGJNQTZIcN3irS9JXfYWeAM2","location_type":"childcare","name":"Blokkendoos","organisation_id":"6KIQKVeFVTK5ADjsyAfI","updated_at":{"__time__":"2024-12-02T22:00:00.000Z"},"updated_by":"QkfQFGJNQTZIcN3irS9JXfYWeAM2","__collections__":{}},"EnYeBJY4UIm38sL2EiNj":{"__collections__":{}},"GzG9vxL5U0bL7CluFzBM":{"address_city":null,"address_country":null,"address_line1":null,"address_line2":null,"address_postal_code":null,"address_region":null,"created_at":{"__time__":"2025-03-03T17:26:50.510Z"},"created_by":"6kOB3lYQlqeD8WHlANXcUVc2Z7v1","location_type":"location","name":"Pauw","organisation_id":"MS8A9c8gHKKJF4W7LzeZ","updated_at":{"__time__":"2025-03-03T17:26:50.510Z"},"updated_by":"6kOB3lYQlqeD8WHlANXcUVc2Z7v1","__collections__":{}},"IhJdmHYD1RgyHz17ScIB":{"address_city":null,"address_country":null,"address_line1":null,"address_line2":null,"address_postal_code":null,"address_region":null,"created_at":{"__time__":"2025-03-03T17:16:40.147Z"},"created_by":"6kOB3lYQlqeD8WHlANXcUVc2Z7v1","location_type":"location","name":"KDV Knikkebol","organisation_id":"TEINbvmlbCMJvXCrYPcn","updated_at":{"__time__":"2025-03-03T17:16:40.147Z"},"updated_by":"6kOB3lYQlqeD8WHlANXcUVc2Z7v1","__collections__":{}},"J5USeqeFKh3vN4F1CSkx":{"address_city":null,"address_country":null,"address_line1":null,"address_line2":null,"address_postal_code":null,"address_region":null,"created_at":{"__time__":"2024-07-03T15:56:49.789Z"},"created_by":"","location_type":"location","name":"De Kaboutertuin","organisation_id":"QaGXPwQLLLdQp3L1FGAL","updated_at":{"__time__":"2024-07-03T15:56:49.789Z"},"updated_by":"","__collections__":{}},"Nr77Ni3kqA0kbprbxLNN":{"address_city":null,"address_country":null,"address_line1":null,"address_line2":null,"address_postal_code":null,"address_region":null,"created_at":{"__time__":"2025-03-03T17:16:40.147Z"},"created_by":"6kOB3lYQlqeD8WHlANXcUVc2Z7v1","location_type":"location","name":"POA Stuiterbol","organisation_id":"TEINbvmlbCMJvXCrYPcn","updated_at":{"__time__":"2025-03-03T17:16:40.147Z"},"updated_by":"6kOB3lYQlqeD8WHlANXcUVc2Z7v1","__collections__":{}},"PdCBU1M7geNQDIulAmqk":{"address_city":null,"address_country":null,"address_line1":null,"address_line2":null,"address_postal_code":null,"address_region":null,"created_at":{"__time__":"2025-03-03T17:16:40.147Z"},"created_by":"6kOB3lYQlqeD8WHlANXcUVc2Z7v1","location_type":"location","name":"KDV Stoombol","organisation_id":"TEINbvmlbCMJvXCrYPcn","updated_at":{"__time__":"2025-03-03T17:16:40.147Z"},"updated_by":"6kOB3lYQlqeD8WHlANXcUVc2Z7v1","__collections__":{}},"QTVOIC93el9maySXxSQH":{"address_city":null,"address_country":null,"address_line1":null,"address_line2":null,"address_postal_code":null,"address_region":null,"created_at":{"__time__":"2025-02-19T16:17:08.278Z"},"created_by":"6kOB3lYQlqeD8WHlANXcUVc2Z7v1","location_type":"location","name":"Van der Parrastraat","organisation_id":"G7BkXTuV6xKtvFdmTFsz","updated_at":{"__time__":"2025-02-19T16:17:08.278Z"},"updated_by":"6kOB3lYQlqeD8WHlANXcUVc2Z7v1","__collections__":{}},"SirAvbSd1JdS1QB0zMfv":{"address_city":null,"address_country":null,"address_line1":null,"address_line2":null,"address_postal_code":null,"address_region":null,"created_at":{"__time__":"2025-03-03T17:16:40.147Z"},"created_by":"6kOB3lYQlqeD8WHlANXcUVc2Z7v1","location_type":"location","name":"POA Holderdebolder","organisation_id":"TEINbvmlbCMJvXCrYPcn","updated_at":{"__time__":"2025-03-03T17:16:40.147Z"},"updated_by":"6kOB3lYQlqeD8WHlANXcUVc2Z7v1","__collections__":{}},"TWqTYoUKfFY9tNPQb6S7":{"address_city":null,"address_country":null,"address_line1":null,"address_line2":null,"address_postal_code":null,"address_region":null,"created_at":{"__time__":"2024-07-03T15:57:00.669Z"},"created_by":"","location_type":"location","name":"De Zonnetuin","organisation_id":"QaGXPwQLLLdQp3L1FGAL","updated_at":{"__time__":"2024-07-03T15:57:00.669Z"},"updated_by":"","__collections__":{}},"TxN4RMDUUnmh0hfv61q9":{"address_city":null,"address_country":null,"address_line1":null,"address_line2":null,"address_postal_code":null,"address_region":null,"created_at":{"__time__":"2025-02-19T16:17:08.278Z"},"created_by":"6kOB3lYQlqeD8WHlANXcUVc2Z7v1","location_type":"location","name":"Van Ruysbroekstraat","organisation_id":"G7BkXTuV6xKtvFdmTFsz","updated_at":{"__time__":"2025-02-19T16:17:08.278Z"},"updated_by":"6kOB3lYQlqeD8WHlANXcUVc2Z7v1","__collections__":{}},"VczsDScsFJ0nPPqKLytg":{"address_city":null,"address_country":null,"address_line1":null,"address_line2":null,"address_postal_code":null,"address_region":null,"created_at":{"__time__":"2025-03-03T17:16:40.147Z"},"created_by":"6kOB3lYQlqeD8WHlANXcUVc2Z7v1","location_type":"location","name":"POA Stoombol","organisation_id":"TEINbvmlbCMJvXCrYPcn","updated_at":{"__time__":"2025-03-03T17:16:40.147Z"},"updated_by":"6kOB3lYQlqeD8WHlANXcUVc2Z7v1","__collections__":{}},"WPJDc8rR94ja0Ke58ErF":{"address_city":"Breda","address_country":"Netherlands","address_line1":"Monseigneur de Vetstraat 2a","address_line2":"","address_postal_code":"4817 JP","address_region":"Noord-Brabant","created_at":{"__time__":"2024-12-05T22:00:00.000Z"},"created_by":"QkfQFGJNQTZIcN3irS9JXfYWeAM2","location_type":"childcare","name":"Harlekijn","organisation_id":"6KIQKVeFVTK5ADjsyAfI","updated_at":{"__time__":"2024-12-05T22:00:00.000Z"},"updated_by":"QkfQFGJNQTZIcN3irS9JXfYWeAM2","__collections__":{}},"Wg2eZ3JUFDVrTMKFcphx":{"address_city":"Breda","address_country":"Netherlands","address_line1":"Cornelis Florisstraat 25","address_line2":"","address_postal_code":"4827 CN","address_region":"Noord-Brabant","created_at":{"__time__":"2024-12-02T22:00:00.000Z"},"created_by":"QkfQFGJNQTZIcN3irS9JXfYWeAM2","location_type":"childcare","name":"Noorderlicht","organisation_id":"6KIQKVeFVTK5ADjsyAfI","updated_at":{"__time__":"2024-12-02T22:00:00.000Z"},"updated_by":"QkfQFGJNQTZIcN3irS9JXfYWeAM2","__collections__":{}},"XXDwdiY0Lw4c9yoqXjkz":{"address_city":null,"address_country":null,"address_line1":null,"address_line2":null,"address_postal_code":null,"address_region":null,"created_at":{"__time__":"2025-03-03T17:16:40.147Z"},"created_by":"6kOB3lYQlqeD8WHlANXcUVc2Z7v1","location_type":"location","name":"POA Bolleboos","organisation_id":"TEINbvmlbCMJvXCrYPcn","updated_at":{"__time__":"2025-03-03T17:16:40.147Z"},"updated_by":"6kOB3lYQlqeD8WHlANXcUVc2Z7v1","__collections__":{}},"Y4gEehhbPgfa7H2byYg8":{"address_city":null,"address_country":null,"address_line1":null,"address_line2":null,"address_postal_code":null,"address_region":null,"created_at":{"__time__":"2025-01-23T20:43:42.992Z"},"created_by":"wTU25DhANfjrJuUVsfFcFrxcv6xF","location_type":"childcare","name":"Burg. van Gentsingel","organisation_id":"aCLqsMmDTDnaObYWmrs3","updated_at":{"__time__":"2025-02-17T16:00:00.000Z"},"updated_by":"6kOB3lYQlqeD8WHlANXcUVc2Z7v1","__collections__":{}},"ZjNE9uMo4wJle3vnO7hx":{"address_city":"Breda","address_country":"Netherlands","address_line1":"Dirk Hartogstraat 10","address_line2":"","address_postal_code":"4812 GE","address_region":"Noord-Brabant","created_at":{"__time__":"2024-12-02T22:00:00.000Z"},"created_by":"QkfQFGJNQTZIcN3irS9JXfYWeAM2","location_type":"childcare","name":"De Wiebeltjes","organisation_id":"6KIQKVeFVTK5ADjsyAfI","updated_at":{"__time__":"2024-12-02T22:00:00.000Z"},"updated_by":"QkfQFGJNQTZIcN3irS9JXfYWeAM2","__collections__":{}},"aM0jE0mwaBf1k8A6anmA":{"address_city":"","address_country":"","address_line1":"","address_line2":"","address_postal_code":"","address_region":"","created_at":{"__time__":"2024-07-03T15:56:09.416Z"},"created_by":"","location_type":"location","name":"Kleine Waaier","organisation_id":"QaGXPwQLLLdQp3L1FGAL","updated_at":{"__time__":"2024-07-03T15:56:30.291Z"},"updated_by":"","__collections__":{}},"cZuFoplv6ebKAAGFdsbf":{"address_city":null,"address_country":null,"address_line1":null,"address_line2":null,"address_postal_code":null,"address_region":null,"created_at":{"__time__":"2025-03-03T17:16:40.147Z"},"created_by":"6kOB3lYQlqeD8WHlANXcUVc2Z7v1","location_type":"location","name":"POA Knikkebol","organisation_id":"TEINbvmlbCMJvXCrYPcn","updated_at":{"__time__":"2025-03-03T17:16:40.147Z"},"updated_by":"6kOB3lYQlqeD8WHlANXcUVc2Z7v1","__collections__":{}},"dB7BxCoIp3wM2xymRVRH":{"address_city":null,"address_country":null,"address_line1":null,"address_line2":null,"address_postal_code":null,"address_region":null,"created_at":{"__time__":"2025-02-19T16:17:08.278Z"},"created_by":"6kOB3lYQlqeD8WHlANXcUVc2Z7v1","location_type":"location","name":"Jaap Hoekdreef","organisation_id":"G7BkXTuV6xKtvFdmTFsz","updated_at":{"__time__":"2025-02-19T16:17:08.278Z"},"updated_by":"6kOB3lYQlqeD8WHlANXcUVc2Z7v1","__collections__":{}},"fHkDHsrUSHyhkYeoamZk":{"address_city":null,"address_country":null,"address_line1":null,"address_line2":null,"address_postal_code":null,"address_region":null,"created_at":{"__time__":"2025-03-03T17:16:40.147Z"},"created_by":"6kOB3lYQlqeD8WHlANXcUVc2Z7v1","location_type":"location","name":"KDV Olke Bolke","organisation_id":"TEINbvmlbCMJvXCrYPcn","updated_at":{"__time__":"2025-03-03T17:16:40.147Z"},"updated_by":"6kOB3lYQlqeD8WHlANXcUVc2Z7v1","__collections__":{}},"itTtmVIQmew1pIuwhHGh":{"address_city":null,"address_country":null,"address_line1":null,"address_line2":null,"address_postal_code":null,"address_region":null,"created_at":{"__time__":"2024-07-03T15:57:21.290Z"},"created_by":"","location_type":"location","name":"De Kennedy","organisation_id":"QaGXPwQLLLdQp3L1FGAL","updated_at":{"__time__":"2024-07-03T15:57:21.290Z"},"updated_by":"","__collections__":{}},"m1rQlKSIVQYjWNs2kxdH":{"address_city":null,"address_country":null,"address_line1":null,"address_line2":null,"address_postal_code":null,"address_region":null,"created_at":{"__time__":"2025-03-03T17:16:40.147Z"},"created_by":"6kOB3lYQlqeD8WHlANXcUVc2Z7v1","location_type":"location","name":"KDV Rollebol","organisation_id":"TEINbvmlbCMJvXCrYPcn","updated_at":{"__time__":"2025-03-03T17:16:40.147Z"},"updated_by":"6kOB3lYQlqeD8WHlANXcUVc2Z7v1","__collections__":{}},"mL0Gpok4ALge1QKVZ42j":{"address_city":"Breda","address_country":"Netherlands","address_line1":"Kapelstraat 15","address_line2":"","address_postal_code":"4817 NX","address_region":"Noord-Brabant","created_at":{"__time__":"2024-12-02T22:00:00.000Z"},"created_by":"QkfQFGJNQTZIcN3irS9JXfYWeAM2","location_type":"childcare","name":"Tweesprong","organisation_id":"6KIQKVeFVTK5ADjsyAfI","updated_at":{"__time__":"2024-12-02T22:00:00.000Z"},"updated_by":"QkfQFGJNQTZIcN3irS9JXfYWeAM2","__collections__":{}},"nk7k9FI07jFpwKMWET5R":{"address_city":null,"address_country":null,"address_line1":null,"address_line2":null,"address_postal_code":null,"address_region":null,"created_at":{"__time__":"2025-02-19T16:17:08.278Z"},"created_by":"6kOB3lYQlqeD8WHlANXcUVc2Z7v1","location_type":"location","name":"Laan Copes","organisation_id":"G7BkXTuV6xKtvFdmTFsz","updated_at":{"__time__":"2025-02-19T16:17:08.278Z"},"updated_by":"6kOB3lYQlqeD8WHlANXcUVc2Z7v1","__collections__":{}},"ozfW6XnTdXHVhXKNZTud":{"address_city":null,"address_country":null,"address_line1":null,"address_line2":null,"address_postal_code":null,"address_region":null,"created_at":{"__time__":"2025-02-17T16:00:00.000Z"},"created_by":"6kOB3lYQlqeD8WHlANXcUVc2Z7v1","location_type":"childcare","name":"Balans","organisation_id":"pHUYevfe97WXKZOhQtxu","updated_at":{"__time__":"2025-02-17T16:00:00.000Z"},"updated_by":"6kOB3lYQlqeD8WHlANXcUVc2Z7v1","__collections__":{}},"pBs4IqauUYthMzVffA8e":{"address_city":null,"address_country":null,"address_line1":null,"address_line2":null,"address_postal_code":null,"address_region":null,"created_at":{"__time__":"2025-03-03T17:26:50.510Z"},"created_by":"6kOB3lYQlqeD8WHlANXcUVc2Z7v1","location_type":"location","name":"Wiekslag","organisation_id":"MS8A9c8gHKKJF4W7LzeZ","updated_at":{"__time__":"2025-03-03T17:26:50.510Z"},"updated_by":"6kOB3lYQlqeD8WHlANXcUVc2Z7v1","__collections__":{}},"pEjeJL11WKRQqKCwa1aB":{"address_city":null,"address_country":null,"address_line1":null,"address_line2":null,"address_postal_code":null,"address_region":null,"created_at":{"__time__":"2025-03-03T17:16:40.147Z"},"created_by":"6kOB3lYQlqeD8WHlANXcUVc2Z7v1","location_type":"location","name":"KDV Skippybol","organisation_id":"TEINbvmlbCMJvXCrYPcn","updated_at":{"__time__":"2025-03-03T17:16:40.147Z"},"updated_by":"6kOB3lYQlqeD8WHlANXcUVc2Z7v1","__collections__":{}},"pZxQLdm4sfkZuoM2Uk8L":{"address_city":null,"address_country":null,"address_line1":null,"address_line2":null,"address_postal_code":null,"address_region":null,"created_at":{"__time__":"2025-02-19T16:17:08.278Z"},"created_by":"6kOB3lYQlqeD8WHlANXcUVc2Z7v1","location_type":"location","name":"Looierslaan","organisation_id":"G7BkXTuV6xKtvFdmTFsz","updated_at":{"__time__":"2025-02-19T16:17:08.278Z"},"updated_by":"6kOB3lYQlqeD8WHlANXcUVc2Z7v1","__collections__":{}},"qm766VhJQDEsZ18jgDKZ":{"address_city":null,"address_country":null,"address_line1":null,"address_line2":null,"address_postal_code":null,"address_region":null,"created_at":{"__time__":"2025-03-03T17:26:50.510Z"},"created_by":"6kOB3lYQlqeD8WHlANXcUVc2Z7v1","location_type":"location","name":"Bloom","organisation_id":"MS8A9c8gHKKJF4W7LzeZ","updated_at":{"__time__":"2025-03-03T17:26:50.510Z"},"updated_by":"6kOB3lYQlqeD8WHlANXcUVc2Z7v1","__collections__":{}},"t5LCnzja1XjE4FoYKSAu":{"address_city":"Breda","address_country":"Netherlands","address_line1":"Meidoornstraat 113","address_line2":"","address_postal_code":"4814 KB","address_region":"Noord-Brabant","created_at":{"__time__":"2024-12-02T22:00:00.000Z"},"created_by":"QkfQFGJNQTZIcN3irS9JXfYWeAM2","location_type":"childcare","name":"Rupsentuin","organisation_id":"6KIQKVeFVTK5ADjsyAfI","updated_at":{"__time__":"2024-12-02T22:00:00.000Z"},"updated_by":"QkfQFGJNQTZIcN3irS9JXfYWeAM2","__collections__":{}},"tCajoZTS1huRMsxLIhFt":{"address_city":null,"address_country":null,"address_line1":null,"address_line2":null,"address_postal_code":null,"address_region":null,"created_at":{"__time__":"2024-07-03T15:57:29.736Z"},"created_by":"","location_type":"location","name":"St. Jozef","organisation_id":"QaGXPwQLLLdQp3L1FGAL","updated_at":{"__time__":"2024-07-03T15:57:29.736Z"},"updated_by":"","__collections__":{}},"xooMbUqU2NscZlESEsbP":{"address_city":null,"address_country":null,"address_line1":null,"address_line2":null,"address_postal_code":null,"address_region":null,"created_at":{"__time__":"2025-02-19T16:17:08.278Z"},"created_by":"6kOB3lYQlqeD8WHlANXcUVc2Z7v1","location_type":"location","name":"Stille Veerkade","organisation_id":"G7BkXTuV6xKtvFdmTFsz","updated_at":{"__time__":"2025-02-19T16:17:08.278Z"},"updated_by":"6kOB3lYQlqeD8WHlANXcUVc2Z7v1","__collections__":{}},"xp3343PaijJSkFVvahqn":{"address_city":null,"address_country":null,"address_line1":null,"address_line2":null,"address_postal_code":null,"address_region":null,"created_at":{"__time__":"2024-07-03T15:57:39.398Z"},"created_by":"","location_type":"location","name":"’t Centrum","organisation_id":"QaGXPwQLLLdQp3L1FGAL","updated_at":{"__time__":"2024-07-03T15:57:39.398Z"},"updated_by":"","__collections__":{}},"ylgb7W0DPxcDyts2IDMy":{"address_city":null,"address_country":null,"address_line1":null,"address_line2":null,"address_postal_code":null,"address_region":null,"created_at":{"__time__":"2024-07-03T15:57:49.523Z"},"created_by":"","location_type":"location","name":"'t Belhameltje","organisation_id":"QaGXPwQLLLdQp3L1FGAL","updated_at":{"__time__":"2024-07-03T15:57:49.523Z"},"updated_by":"","__collections__":{}}}}